snakemake_executor_plugin_slurm_jobstep/__init__.py
snakemake_executor_plugin_slurm_jobstep-0.2.1.dist-info/LICENSE
snakemake_executor_plugin_slurm_jobstep-0.2.1.dist-info/METADATA
snakemake_executor_plugin_slurm_jobstep-0.2.1.dist-info/WHEEL
snakemake_executor_plugin_slurm_jobstep-0.2.1.dist-info/RECORD
