Metadata-Version: 2.1
Name: snakemake-executor-plugin-slurm-jobstep
Version: 0.2.1
Summary: A Snakemake executor plugin for running srun jobs inside of SLURM jobs (meant for internal use by snakemake-executor-plugin-slurm)
Home-page: https://github.com/snakemake/snakemake-executor-plugin-slurm-jobstep
License: MIT
Keywords: snakemake,plugin,executor,cluster,slurm
Author: Christian Meesters
Author-email: meesters@uni-mainz.de
Requires-Python: >=3.11,<4.0
Classifier: License :: OSI Approved :: MIT License
Classifier: Programming Language :: Python :: 3
Classifier: Programming Language :: Python :: 3.11
Classifier: Programming Language :: Python :: 3.12
Requires-Dist: snakemake-interface-common (>=1.13.0,<2.0.0)
Requires-Dist: snakemake-interface-executor-plugins (>=9.0.0,<10.0.0)
Project-URL: Documentation, https://snakemake.github.io/snakemake-plugin-catalog/plugins/executor/slurm-jobstep.html
Project-URL: Repository, https://github.com/snakemake/snakemake-executor-plugin-slurm-jobstep
